neural_source_filter/__init__.py
neural_source_filter/_hifi_gan.py
neural_source_filter/_model.py
neural_source_filter/py.typed
neural_source_filter-0.1.20.dist-info/LICENSE
neural_source_filter-0.1.20.dist-info/METADATA
neural_source_filter-0.1.20.dist-info/WHEEL
neural_source_filter-0.1.20.dist-info/RECORD
