Metadata-Version: 2.1
Name: neural-source-filter
Version: 0.1.20
Summary: Python package for NSF (unofficial)
Home-page: https://github.com/34j/neural-source-filter
License: BSD-3-Clause
Author: 34j
Author-email: 34j.95a2p@simplelogin.com
Requires-Python: >=3.9,<3.12
Classifier: Development Status :: 2 - Pre-Alpha
Classifier: Intended Audience :: Developers
Classifier: License :: OSI Approved :: BSD License
Classifier: Natural Language :: English
Classifier: Operating System :: OS Independent
Classifier: Programming Language :: Python :: 3
Classifier: Programming Language :: Python :: 3.9
Classifier: Programming Language :: Python :: 3.10
Classifier: Programming Language :: Python :: 3.11
Classifier: Topic :: Software Development :: Libraries
Requires-Dist: numpy (>=1.22.0,<2.0.0)
Requires-Dist: torch (>=2.0.0,<3.0.0,!=2.0.1)
Requires-Dist: tts (>=0.22.0,<0.23.0)
Project-URL: Bug Tracker, https://github.com/34j/neural-source-filter/issues
Project-URL: Changelog, https://github.com/34j/neural-source-filter/blob/main/CHANGELOG.md
Project-URL: Documentation, https://neural-source-filter.readthedocs.io
Project-URL: Repository, https://github.com/34j/neural-source-filter
